sodium/__init__.py
sodium/flame/__init__.py
sodium/metal/__init__.py
code_sodium-0.0.0.post0.dist-info/LICENSE
code_sodium-0.0.0.post0.dist-info/METADATA
code_sodium-0.0.0.post0.dist-info/WHEEL
code_sodium-0.0.0.post0.dist-info/top_level.txt
code_sodium-0.0.0.post0.dist-info/RECORD
