Metadata-Version: 2.1
Name: code-sodium
Version: 0.0.0.post0
Summary: the package of neural networks and utilities
Home-page: https://github.com/YeongHyeon/sodium
Author: YeongHyeon Park
Author-email: young200405@gmail.com
License: UNKNOWN
Download-URL: https://github.com/YeongHyeon/sodium/archive/refs/heads/master.zip
Keywords: sodium
Platform: UNKNOWN
Classifier: Programming Language :: Python :: 3
Requires-Python: >=3
Requires-Dist: numpy (==1.19.5)
Requires-Dist: tensorflow (==2.4.0)
